pycoinbaseapi/__init__.py
pycoinbaseapi/wallet/__init__.py
pycoinbaseapi/wallet/auth.py
pycoinbaseapi/wallet/client.py
pycoinbaseapi/wallet/compat.py
pycoinbaseapi/wallet/error.py
pycoinbaseapi/wallet/model.py
pycoinbaseapi/wallet/util.py
pycoinbaseapi-2.2.2.dist-info/LICENSE
pycoinbaseapi-2.2.2.dist-info/METADATA
pycoinbaseapi-2.2.2.dist-info/WHEEL
pycoinbaseapi-2.2.2.dist-info/top_level.txt
pycoinbaseapi-2.2.2.dist-info/RECORD
